[
  {
    "state": "tn",
    "lastName": "alexander",
    "firstName": "lamar",
    "img": "https://www.congress.gov/img/member/115_sr_tn_alexander_lamar_200.jpg"
  },
  {
    "state": "wi",
    "lastName": "baldwin",
    "firstName": "tammy",
    "img": "https://www.congress.gov/img/member/115_sr_wi_baldwin_tammy_200.jpg"
  },
  {
    "state": "wy",
    "lastName": "barrasso",
    "firstName": "john",
    "img": "https://www.congress.gov/img/member/115_sr_wy_barrasso_john_200.jpg"
  },
  {
    "state": "co",
    "lastName": "bennet",
    "firstName": "michael",
    "img": "https://www.congress.gov/img/member/115_sr_co_bennet_michael_200.jpg"
  },
  {
    "state": "tn",
    "lastName": "blackburn",
    "firstName": "marsha",
    "img": "https://www.congress.gov/img/member/115_rp_tn_7_blackburn_marsha_200.jpg"
  },
  {
    "state": "ct",
    "lastName": "blumenthal",
    "firstName": "richard",
    "img": "https://www.congress.gov/img/member/115_sr_ct_blumenthal_richard_200.jpg"
  },
  {
    "state": "mo",
    "lastName": "blunt",
    "firstName": "roy",
    "img": "https://www.congress.gov/img/member/115_sr_mo_blunt_roy_200.jpg"
  },
  {
    "state": "nj",
    "lastName": "booker",
    "firstName": "cory",
    "img": "https://www.congress.gov/img/member/115_sr_nj_booker_cory_200.jpg"
  },
  {
    "state": "ar",
    "lastName": "boozman",
    "firstName": "john",
    "img": "https://www.congress.gov/img/member/115_sr_ar_boozman_john_200.jpg"
  },
  {
    "state": "oh",
    "lastName": "brown",
    "firstName": "sherrod",
    "img": "https://www.congress.gov/img/member/115_sr_oh_brown_sherrod_200.jpg"
  },
  {
    "state": "nc",
    "lastName": "burr",
    "firstName": "richard",
    "img": "https://www.congress.gov/img/member/115_sr_nc_burr_richard_200.jpg"
  },
  {
    "state": "wa",
    "lastName": "cantwell",
    "firstName": "maria",
    "img": "https://www.congress.gov/img/member/115_sr_wa_cantwell_maria_200.jpg"
  },
  {
    "state": "wv",
    "lastName": "capito",
    "firstName": "shelley moore",
    "img": "https://www.congress.gov/img/member/115_sr_wv_moorecapito_shelly_200.jpg"
  },
  {
    "state": "md",
    "lastName": "cardin",
    "firstName": "benjamin",
    "img": "https://www.congress.gov/img/member/115_sr_md_cardin_benjamin_200.jpg"
  },
  {
    "state": "de",
    "lastName": "carper",
    "firstName": "thomas",
    "img": "https://www.congress.gov/img/member/115_sr_de_carper_thomas_200.jpg"
  },
  {
    "state": "pa",
    "lastName": "casey",
    "firstName": "robert",
    "img": "https://www.congress.gov/img/member/115_sr_pa_casey_robert_200.jpg"
  },
  {
    "state": "la",
    "lastName": "cassidy",
    "firstName": "bill",
    "img": "https://www.congress.gov/img/member/115_sr_la_cassidy_bill_200.jpg"
  },
  {
    "state": "me",
    "lastName": "collins",
    "firstName": "susan",
    "img": "https://www.congress.gov/img/member/115_sr_me_collins_susan_200.jpg"
  },
  {
    "state": "de",
    "lastName": "coons",
    "firstName": "christopher",
    "img": "https://www.congress.gov/img/member/115_sr_de_coons_christopher_200.jpg"
  },
  {
    "state": "tx",
    "lastName": "cornyn",
    "firstName": "john",
    "img": "https://www.congress.gov/img/member/115_sr_tx_cornyn_john_200.jpg"
  },
  {
    "state": "nv",
    "lastName": "cortez_masto",
    "firstName": "catherine",
    "img": "https://www.congress.gov/img/member/115_co_nv_cortezmasto_catherine_200.jpg"
  },
  {
    "state": "ar",
    "lastName": "cotton",
    "firstName": "tom",
    "img": "https://www.congress.gov/img/member/115_sr_ar_cotton_tom_200.jpg"
  },
  {
    "state": "nd",
    "lastName": "cramer",
    "firstName": "kevin",
    "img": "https://www.congress.gov/img/member/115_rp_nd_0_cramer_kevin_200.jpg"
  },
  {
    "state": "id",
    "lastName": "crapo",
    "firstName": "mike",
    "img": "https://www.congress.gov/img/member/115_sr_id_crapo_mike_200.jpg"
  },
  {
    "state": "tx",
    "lastName": "cruz",
    "firstName": "ted",
    "img": "https://www.congress.gov/img/member/115_sr_tx_cruz_ted_200.jpg"
  },
  {
    "state": "mt",
    "lastName": "daines",
    "firstName": "steve",
    "img": "https://www.congress.gov/img/member/115_sr_mt_danes_steve_200.jpg"
  },
  {
    "state": "il",
    "lastName": "duckworth",
    "firstName": "tammy",
    "img": "https://www.congress.gov/img/member/115_sr_il_duckworth_tammy_200.jpg"
  },
  {
    "state": "il",
    "lastName": "durbin",
    "firstName": "richard",
    "img": "https://www.congress.gov/img/member/115_sr_il_durbin_richard_200.jpg"
  },
  {
    "state": "wy",
    "lastName": "enzi",
    "firstName": "mike",
    "img": "https://www.congress.gov/img/member/115_sr_wy_enzi_michael_200.jpg"
  },
  {
    "state": "ia",
    "lastName": "ernst",
    "firstName": "joni",
    "img": "https://www.congress.gov/img/member/115_sr_ia_ernst_joni_200.jpg"
  },
  {
    "state": "ca",
    "lastName": "feinstein",
    "firstName": "dianne",
    "img": "https://www.congress.gov/img/member/115_sr_ca_feinstein_dianne_200.jpg"
  },
  {
    "state": "ne",
    "lastName": "fischer",
    "firstName": "deb",
    "img": "https://www.congress.gov/img/member/115_sr_ne_fischer_deb_200.jpg"
  },
  {
    "state": "co",
    "lastName": "gardner",
    "firstName": "cory",
    "img": "https://www.congress.gov/img/member/115_sr_co_gardner_cory_200.jpg"
  },
  {
    "state": "ny",
    "lastName": "gillibrand",
    "firstName": "kirsten",
    "img": "https://www.congress.gov/img/member/115_sr_ny_gillibrand_kirsten_200.jpg"
  },
  {
    "state": "sc",
    "lastName": "graham",
    "firstName": "lindsey",
    "img": "https://www.congress.gov/img/member/115_sr_sc_graham_lindsey_200.jpg"
  },
  {
    "state": "ia",
    "lastName": "grassley",
    "firstName": "chuck",
    "img": "https://www.congress.gov/img/member/115_sr_ia_grassley_chuck_200.jpg"
  },
  {
    "state": "ca",
    "lastName": "harris",
    "firstName": "kamala",
    "img": "https://www.congress.gov/img/member/115_sr_ca_harris_kamala_200.jpg"
  },
  {
    "state": "nh",
    "lastName": "wood hassan",
    "firstName": "margaret",
    "img": "https://www.congress.gov/img/member/115_sr_nh_hassan_maggie_200.jpg"
  },
  {
    "state": "nm",
    "lastName": "heinrich",
    "firstName": "martin",
    "img": "https://www.congress.gov/img/member/115_sr_nm_heinrich_martin_200.jpg"
  },
  {
    "state": "hi",
    "lastName": "hirono",
    "firstName": "mazie",
    "img": "https://www.congress.gov/img/member/115_sr_hi_hirono_mazie_200.jpg"
  },
  {
    "state": "nd",
    "lastName": "hoeven",
    "firstName": "john",
    "img": "https://www.congress.gov/img/member/115_sr_nd_hoeven_john_200.jpg"
  },
  {
    "state": "ok",
    "lastName": "inhofe",
    "firstName": "jim",
    "img": "https://www.congress.gov/img/member/115_sr_ok_inhofe_james_200.jpg"
  },
  {
    "state": "ga",
    "lastName": "isakson",
    "firstName": "johnny",
    "img": "https://www.congress.gov/img/member/115_sr_ga_isakson_johnny_200.jpg"
  },
  {
    "state": "wi",
    "lastName": "johnson",
    "firstName": "ron",
    "img": "https://www.congress.gov/img/member/115_sr_wi_johnson_ron_200.jpg"
  },
  {
    "state": "al",
    "lastName": "jones",
    "firstName": "doug",
    "img": "https://www.congress.gov/img/member/115_sr_al_jones_doug_200.jpg"
  },
  {
    "state": "va",
    "lastName": "kaine",
    "firstName": "tim",
    "img": "https://www.congress.gov/img/member/115_sr_va_kaine_tim_200.jpg"
  },
  {
    "state": "la",
    "lastName": "kennedy",
    "firstName": "john",
    "img": "https://www.congress.gov/img/member/115_sr_la_kennedy_john_200.jpg"
  },
  {
    "state": "me",
    "lastName": "king",
    "firstName": "angus",
    "img": "https://www.congress.gov/img/member/115_sr_me_kingjr_angus_200.jpg"
  },
  {
    "state": "mn",
    "lastName": "klobuchar",
    "firstName": "amy",
    "img": "https://www.congress.gov/img/member/115_sr_mn_klobuchar_amy_200.jpg"
  },
  {
    "state": "ok",
    "lastName": "lankford",
    "firstName": "james",
    "img": "https://www.congress.gov/img/member/115_sr_ok_lankford_james_200.jpg"
  },
  {
    "state": "vt",
    "lastName": "leahy",
    "firstName": "patrick",
    "img": "https://www.congress.gov/img/member/115_sr_vt_leahy_patrick_200.jpg"
  },
  {
    "state": "ut",
    "lastName": "lee",
    "firstName": "mike",
    "img": "https://www.congress.gov/img/member/115_sr_ut_lee_michael_200.jpg"
  },
  {
    "state": "wv",
    "lastName": "manchin",
    "firstName": "joe",
    "img": "https://www.congress.gov/img/member/115_sr_wv_manchin_joe_200.jpg"
  },
  {
    "state": "ma",
    "lastName": "markey",
    "firstName": "edward",
    "img": "https://www.congress.gov/img/member/115_sr_ma_markey_edward_200.jpg"
  },
  {
    "state": "ky",
    "lastName": "mcconnell",
    "firstName": "mitch",
    "img": "https://www.congress.gov/img/member/115_sr_ky_mcconnell_mitch_200.jpg"
  },
  {
    "state": "az",
    "lastName": "mcsally",
    "firstName": "martha",
    "img": "https://www.congress.gov/img/member/115_rp_az_2_mcsally_martha_200.jpg"
  },
  {
    "state": "nj",
    "lastName": "menendez",
    "firstName": "robert",
    "img": "https://www.congress.gov/img/member/115_sr_nj_menendez_robert_200.jpg"
  },
  {
    "state": "or",
    "lastName": "merkley",
    "firstName": "jeff",
    "img": "https://www.congress.gov/img/member/115_sr_or_merkley_jeff_200.jpg"
  },
  {
    "state": "ks",
    "lastName": "moran",
    "firstName": "jerry",
    "img": "https://www.congress.gov/img/member/115_sr_ks_moran_jerry_200.jpg"
  },
  {
    "state": "ak",
    "lastName": "murkowski",
    "firstName": "lisa",
    "img": "https://www.congress.gov/img/member/115_sr_ak_murkowski_lisa_200.jpg"
  },
  {
    "state": "ct",
    "lastName": "murphy",
    "firstName": "christopher",
    "img": "https://www.congress.gov/img/member/115_sr_ct_murphy_christopher_200.jpg"
  },
  {
    "state": "wa",
    "lastName": "murray",
    "firstName": "patty",
    "img": "https://www.congress.gov/img/member/115_sr_wa_murray_patty_200.jpg"
  },
  {
    "state": "ky",
    "lastName": "paul",
    "firstName": "rand",
    "img": "https://www.congress.gov/img/member/115_sr_ky_paul_rand_200.jpg"
  },
  {
    "state": "ga",
    "lastName": "perdue",
    "firstName": "david",
    "img": "https://www.congress.gov/img/member/115_sr_ga_perdue_david_200.jpg"
  },
  {
    "state": "mi",
    "lastName": "peters",
    "firstName": "gary",
    "img": "https://www.congress.gov/img/member/115_sr_mi_peters_gary_200.jpg"
  },
  {
    "state": "oh",
    "lastName": "portman",
    "firstName": "rob",
    "img": "https://www.congress.gov/img/member/115_sr_oh_portman_rob_200.jpg"
  },
  {
    "state": "ri",
    "lastName": "reed",
    "firstName": "jack",
    "img": "https://www.congress.gov/img/member/115_sr_ri_reed_jack_200.jpg"
  },
  {
    "state": "id",
    "lastName": "risch",
    "firstName": "jim",
    "img": "https://www.congress.gov/img/member/115_sr_id_risch_james_200.jpg"
  },
  {
    "state": "ks",
    "lastName": "roberts",
    "firstName": "pat",
    "img": "https://www.congress.gov/img/member/115_sr_ks_roberts_pat_200.jpg"
  },
  {
    "state": "nv",
    "lastName": "rosen",
    "firstName": "jacky",
    "img": "https://www.congress.gov/img/member/115_rp_nv_3_rosen_jacky_200.jpg"
  },
  {
    "state": "sd",
    "lastName": "rounds",
    "firstName": "mike",
    "img": "https://www.congress.gov/img/member/115_sr_sd_rounds_mike_200.jpg"
  },
  {
    "state": "fl",
    "lastName": "rubio",
    "firstName": "marco",
    "img": "https://www.congress.gov/img/member/115_sr_fl_rubio_marco_200.jpg"
  },
  {
    "state": "vt",
    "lastName": "sanders",
    "firstName": "bernard",
    "img": "https://www.congress.gov/img/member/115_sr_vt_sanders_bernard_200.jpg"
  },
  {
    "state": "ne",
    "lastName": "sasse",
    "firstName": "ben",
    "img": "https://www.congress.gov/img/member/115_sr_ne_sasse_ben_200.jpg"
  },
  {
    "state": "hi",
    "lastName": "schatz",
    "firstName": "brian",
    "img": "https://www.congress.gov/img/member/115_sr_hi_schatz_brian_200.jpg"
  },
  {
    "state": "ny",
    "lastName": "schumer",
    "firstName": "charles",
    "img": "https://www.congress.gov/img/member/115_sr_ny_schumer_charles_200.jpg"
  },
  {
    "state": "sc",
    "lastName": "scott",
    "firstName": "tim",
    "img": "https://www.congress.gov/img/member/115_sr_sc_scott_tim_200.jpg"
  },
  {
    "state": "nh",
    "lastName": "shaheen",
    "firstName": "jeanne",
    "img": "https://www.congress.gov/img/member/115_sr_nh_shaheen_jeanne_200.jpg"
  },
  {
    "state": "al",
    "lastName": "shelby",
    "firstName": "richard",
    "img": "https://www.congress.gov/img/member/115_sr_al_shelby_richard_200.jpg"
  },
  {
    "state": "az",
    "lastName": "sinema",
    "firstName": "kyrsten",
    "img": "https://www.congress.gov/img/member/115_sr_az_sinema_kyrsten_200.jpg"
  },
  {
    "state": "mn",
    "lastName": "smith",
    "firstName": "tina",
    "img": "https://www.congress.gov/img/member/115_sr_mn_smith_tina_200.jpg"
  },
  {
    "state": "mi",
    "lastName": "stabenow",
    "firstName": "debbie",
    "img": "https://www.congress.gov/img/member/115_sr_mi_stabenow_debbie_200.jpg"
  },
  {
    "state": "ak",
    "lastName": "sullivan",
    "firstName": "dan",
    "img": "https://www.congress.gov/img/member/115_sr_ak_sullivan_dan_200.jpg"
  },
  {
    "state": "mt",
    "lastName": "tester",
    "firstName": "jon",
    "img": "https://www.congress.gov/img/member/115_sr_mt_tester_jon_200.jpg"
  },
  {
    "state": "sd",
    "lastName": "thune",
    "firstName": "john",
    "img": "https://www.congress.gov/img/member/115_sr_sd_thune_john_200.jpg"
  },
  {
    "state": "nc",
    "lastName": "tillis",
    "firstName": "thom",
    "img": "https://www.congress.gov/img/member/115_sr_nc_tillis_thom_200.jpg"
  },
  {
    "state": "pa",
    "lastName": "toomey",
    "firstName": "pat",
    "img": "https://www.congress.gov/img/member/115_sr_pa_toomey_pat_200.jpg"
  },
  {
    "state": "nm",
    "lastName": "udall",
    "firstName": "tom",
    "img": "https://www.congress.gov/img/member/115_sr_nm_udall_tom_200.jpg"
  },
  {
    "state": "md",
    "lastName": "van hollen",
    "firstName": "chris",
    "img": "https://www.congress.gov/img/member/115_sr_md_vanhollen_chris_200.jpg"
  },
  {
    "state": "va",
    "lastName": "warner",
    "firstName": "mark",
    "img": "https://www.congress.gov/img/member/115_sr_va_warner_mark_200.jpg"
  },
  {
    "state": "ma",
    "lastName": "warren",
    "firstName": "elizabeth",
    "img": "https://www.congress.gov/img/member/115_sr_ma_warren_elizabeth_200.jpg"
  },
  {
    "state": "ri",
    "lastName": "whitehouse",
    "firstName": "sheldon",
    "img": "https://www.congress.gov/img/member/115_sr_ri_whitehouse_sheldon_200.jpg"
  },
  {
    "state": "ms",
    "lastName": "wicker",
    "firstName": "roger",
    "img": "https://www.congress.gov/img/member/115_sr_ms_wicker_roger_200.jpg"
  },
  {
    "state": "or",
    "lastName": "wyden",
    "firstName": "ron",
    "img": "https://www.congress.gov/img/member/115_sr_or_wyden_ron_200.jpg"
  },
  {
    "state": "in",
    "lastName": "young",
    "firstName": "todd",
    "img": "https://www.congress.gov/img/member/115_sr_in_young_todd_200.jpg"
  },
  {
    "state": "fl",
    "lastName": "scott",
    "firstName": "rick",
    "img": "https://www.congress.gov/img/member/s001217_200.jpg"
  },
  {
    "state": "ut",
    "lastName": "romney",
    "firstName": "mitt",
    "img": "https://www.congress.gov/img/member/r000615_200.jpg"
  },
  {
    "state": "ga",
    "lastName": "loeffler",
    "firstName": "kelly",
    "img": "https://www.congress.gov/img/member/l000594_200.jpg"
  },
  {
    "state": "ms",
    "lastName": "hyde-smith",
    "firstName": "cindy",
    "img": "https://www.congress.gov/img/member/h001079_200.jpg"
  },
  {
    "state": "mo",
    "lastName": "hawley",
    "firstName": "josh",
    "img": "https://www.congress.gov/img/member/h001089_200.jpg"
  },
  {
    "state": "ia",
    "lastName": "braun",
    "firstName": "mike",
    "img": "https://www.congress.gov/img/member/b001310_200.jpg"
  }
]
